fastapi_qp/__init__.py
fastapi_qp/query_param.py
fastapi_qp-0.2.0.dist-info/WHEEL
fastapi_qp-0.2.0.dist-info/METADATA
fastapi_qp-0.2.0.dist-info/RECORD
